pyrival/__init__.py
pyrival/version.py
pyrival/algebra/__init__.py
pyrival/algebra/chinese_remainder.py
pyrival/algebra/discrete_log.py
pyrival/algebra/factors.py
pyrival/algebra/fft.py
pyrival/algebra/fst.py
pyrival/algebra/gcd.py
pyrival/algebra/is_prime.py
pyrival/algebra/mod_sqrt.py
pyrival/algebra/modinv.py
pyrival/algebra/ntt.py
pyrival/algebra/phi.py
pyrival/algebra/primitive_root.py
pyrival/algebra/sieve.py
pyrival/combinatorics/__init__.py
pyrival/combinatorics/combinatorics.py
pyrival/combinatorics/nCr_mod.py
pyrival/combinatorics/partitions.py
pyrival/data_structures/BitArray.py
pyrival/data_structures/CFraction.py
pyrival/data_structures/DisjointSetUnion.py
pyrival/data_structures/FenwickTree.py
pyrival/data_structures/Fraction.py
pyrival/data_structures/Heap.py
pyrival/data_structures/LazySegmentTree.py
pyrival/data_structures/LinkedList.py
pyrival/data_structures/Node.py
pyrival/data_structures/PersistentSegTree.py
pyrival/data_structures/RangeQuery.py
pyrival/data_structures/SegmentTree.py
pyrival/data_structures/SortedList.py
pyrival/data_structures/Treap.py
pyrival/data_structures/Trie.py
pyrival/data_structures/TwoSat.py
pyrival/data_structures/__init__.py
pyrival/data_structures/convex_hull_trick.py
pyrival/data_structures/tree_repr.py
pyrival/geometry/__init__.py
pyrival/geometry/convex_hull.py
pyrival/geometry/lines.py
pyrival/geometry/polygons.py
pyrival/geometry/vectors.py
pyrival/graphs/__init__.py
pyrival/graphs/bellman_ford.py
pyrival/graphs/bfs.py
pyrival/graphs/components.py
pyrival/graphs/cycle_finding.py
pyrival/graphs/dfs.py
pyrival/graphs/dijkstra.py
pyrival/graphs/dinic.py
pyrival/graphs/euler_walk.py
pyrival/graphs/find_path.py
pyrival/graphs/floyd_warshall.py
pyrival/graphs/hopcroft_karp.py
pyrival/graphs/is_bipartite.py
pyrival/graphs/kruskal.py
pyrival/graphs/lca.py
pyrival/graphs/maximum_matching.py
pyrival/graphs/prim.py
pyrival/graphs/scc.py
pyrival/graphs/toposort.py
pyrival/linear_algebra/__init__.py
PyRival-0.2.0.dist-info/LICENSE
PyRival-0.2.0.dist-info/METADATA
PyRival-0.2.0.dist-info/WHEEL
PyRival-0.2.0.dist-info/entry_points.txt
PyRival-0.2.0.dist-info/top_level.txt
PyRival-0.2.0.dist-info/RECORD
