Metadata-Version: 2.1
Name: PyRival
Version: 0.2.0
Summary: Competitive Programming Library
Home-page: https://github.com/cheran-senthil/PyRival
Author: Cheran Senthil
Author-email: cheran.v.senthil@gmail.com
License: UNKNOWN
Keywords: competitive-programming,data-structures,algorithms
Platform: UNKNOWN
Classifier: Development Status :: 4 - Beta
Classifier: License :: OSI Approved :: Apache Software License
Classifier: Operating System :: OS Independent
Classifier: Programming Language :: Python
Classifier: Programming Language :: Python :: 3
Classifier: Programming Language :: Python :: 3.4
Classifier: Programming Language :: Python :: 3.5
Classifier: Programming Language :: Python :: 3.6
Classifier: Programming Language :: Python :: 3.7
Classifier: Programming Language :: Python :: 3.8
Classifier: Programming Language :: Python :: 3 :: Only
Classifier: Programming Language :: Python :: Implementation :: CPython
Classifier: Programming Language :: Python :: Implementation :: PyPy
